CONTRIBUTING.rst
LICENSE
MANIFEST.in
README.md
setup.cfg
setup.py
nlpeasy/__init__.py
nlpeasy/docker.py
nlpeasy/elastic.py
nlpeasy/html.py
nlpeasy/kibana.py
nlpeasy/language.py
nlpeasy/pipeline.py
nlpeasy/util.py
nlpeasy.egg-info/PKG-INFO
nlpeasy.egg-info/SOURCES.txt
nlpeasy.egg-info/dependency_links.txt
nlpeasy.egg-info/not-zip-safe
nlpeasy.egg-info/requires.txt
nlpeasy.egg-info/top_level.txt
tests/test_nlpeasy.py