Metadata-Version: 2.1
Name: nlpeasy
Version: 0.6.2
Summary: Easy Peasy Language Squeezy
Home-page: https://github.com/d-one/nlpeasy
Author: Philipp Thomann
Author-email: philipp.thomann@d-one.ai
License: Apache Software License 2.0
Keywords: nlpeasy
Platform: UNKNOWN
Classifier: Development Status :: 3 - Alpha
Classifier: Intended Audience :: Developers
Classifier: License :: OSI Approved :: Apache Software License
Classifier: Natural Language :: English
Classifier: Programming Language :: Python :: 3
Classifier: Programming Language :: Python :: 3.6
Classifier: Programming Language :: Python :: 3.7
Classifier: Topic :: Scientific/Engineering :: Artificial Intelligence
Classifier: Topic :: Text Processing :: Markup :: HTML
